{
	"info": {
		"_postman_id": "9982f446-76c9-4742-8bca-ac3a1a231232",
		"name": "Final Capstone",
		"schema": "https://schema.getpostman.com/json/collection/v2.1.0/collection.json",
		"_exporter_id": "30609949"
	},
	"item": [
		{
			"name": "Register New User",
			"request": {
				"method": "POST",
				"header": [],
				"body": {
					"mode": "raw",
					"raw": "{\r\n    \"username\": \"rich\",\r\n    \"password\": \"rich\",\r\n    \"confirmPassword\": \"rich\",\r\n    \"role\": \"ROLE_USER\"\r\n}",
					"options": {
						"raw": {
							"language": "json"
						}
					}
				},
				"url": {
					"raw": "localhost:9000/register",
					"host": [
						"localhost"
					],
					"port": "9000",
					"path": [
						"register"
					]
				}
			},
			"response": []
		},
		{
			"name": "Login User",
			"request": {
				"method": "POST",
				"header": [],
				"body": {
					"mode": "raw",
					"raw": "{\r\n    \"username\": \"rich\",\r\n    \"password\": \"rich\"\r\n}",
					"options": {
						"raw": {
							"language": "json"
						}
					}
				},
				"url": {
					"raw": "localhost:9000/login",
					"host": [
						"localhost"
					],
					"port": "9000",
					"path": [
						"login"
					]
				}
			},
			"response": []
		},
		{
			"name": "Admin",
			"request": {
				"method": "POST",
				"header": [],
				"body": {
					"mode": "raw",
					"raw": "{\r\n    \"username\": \"admin\",\r\n    \"password\": \"password\"\r\n}",
					"options": {
						"raw": {
							"language": "json"
						}
					}
				},
				"url": {
					"raw": "localhost:9000/login",
					"host": [
						"localhost"
					],
					"port": "9000",
					"path": [
						"login"
					]
				}
			},
			"response": []
		},
		{
			"name": "Delete User",
			"request": {
				"method": "DELETE",
				"header": [],
				"body": {
					"mode": "raw",
					"raw": "{\r\n    \"username\": \"admin\",\r\n    \"password\": \"password\"\r\n}",
					"options": {
						"raw": {
							"language": "json"
						}
					}
				},
				"url": {
					"raw": "localhost:9000/user/1",
					"host": [
						"localhost"
					],
					"port": "9000",
					"path": [
						"user",
						"1"
					]
				}
			},
			"response": []
		},
		{
			"name": "Delete Game",
			"request": {
				"method": "DELETE",
				"header": [],
				"body": {
					"mode": "raw",
					"raw": "{\r\n    \"username\": \"admin\",\r\n    \"password\": \"password\"\r\n}",
					"options": {
						"raw": {
							"language": "json"
						}
					}
				},
				"url": {
					"raw": "localhost:9000/game/1512",
					"host": [
						"localhost"
					],
					"port": "9000",
					"path": [
						"game",
						"1512"
					]
				}
			},
			"response": []
		},
		{
			"name": "Get Game",
			"protocolProfileBehavior": {
				"disableBodyPruning": true
			},
			"request": {
				"method": "GET",
				"header": [],
				"body": {
					"mode": "raw",
					"raw": "{\r\n    \"username\": \"admin\",\r\n    \"password\": \"password\"\r\n}",
					"options": {
						"raw": {
							"language": "json"
						}
					}
				},
				"url": {
					"raw": "localhost:9000/game/1512",
					"host": [
						"localhost"
					],
					"port": "9000",
					"path": [
						"game",
						"1512"
					]
				}
			},
			"response": []
		},
		{
			"name": "Get Random Game",
			"protocolProfileBehavior": {
				"disableBodyPruning": true
			},
			"request": {
				"method": "GET",
				"header": [],
				"body": {
					"mode": "raw",
					"raw": "{\r\n    \"username\": \"admin\",\r\n    \"password\": \"password\"\r\n}",
					"options": {
						"raw": {
							"language": "json"
						}
					}
				},
				"url": {
					"raw": "localhost:9000/game/1512",
					"host": [
						"localhost"
					],
					"port": "9000",
					"path": [
						"game",
						"1512"
					]
				}
			},
			"response": []
		},
		{
			"name": "Get User",
			"protocolProfileBehavior": {
				"disableBodyPruning": true
			},
			"request": {
				"method": "GET",
				"header": [],
				"body": {
					"mode": "raw",
					"raw": "{\r\n    \"username\": \"admin\",\r\n    \"password\": \"password\"\r\n}",
					"options": {
						"raw": {
							"language": "json"
						}
					}
				},
				"url": {
					"raw": "localhost:9000/game/1512",
					"host": [
						"localhost"
					],
					"port": "9000",
					"path": [
						"game",
						"1512"
					]
				}
			},
			"response": []
		},
		{
			"name": "Get Comments For Review",
			"protocolProfileBehavior": {
				"disableBodyPruning": true
			},
			"request": {
				"method": "GET",
				"header": [],
				"body": {
					"mode": "raw",
					"raw": "{\r\n    \"username\": \"admin\",\r\n    \"password\": \"password\"\r\n}",
					"options": {
						"raw": {
							"language": "json"
						}
					}
				},
				"url": {
					"raw": "localhost:9000/review/1/comments",
					"host": [
						"localhost"
					],
					"port": "9000",
					"path": [
						"review",
						"1",
						"comments"
					]
				}
			},
			"response": []
		},
		{
			"name": "Get Comment",
			"protocolProfileBehavior": {
				"disableBodyPruning": true
			},
			"request": {
				"method": "GET",
				"header": [],
				"body": {
					"mode": "raw",
					"raw": "{\r\n    \"username\": \"admin\",\r\n    \"password\": \"password\"\r\n}",
					"options": {
						"raw": {
							"language": "json"
						}
					}
				},
				"url": {
					"raw": "localhost:9000/comment/1",
					"host": [
						"localhost"
					],
					"port": "9000",
					"path": [
						"comment",
						"1"
					]
				}
			},
			"response": []
		},
		{
			"name": "Get Reviews For Game",
			"protocolProfileBehavior": {
				"disableBodyPruning": true
			},
			"request": {
				"method": "GET",
				"header": [],
				"body": {
					"mode": "raw",
					"raw": "{\r\n    \"username\": \"admin\",\r\n    \"password\": \"password\"\r\n}",
					"options": {
						"raw": {
							"language": "json"
						}
					}
				},
				"url": {
					"raw": "localhost:9000/game/1/reviews",
					"host": [
						"localhost"
					],
					"port": "9000",
					"path": [
						"game",
						"1",
						"reviews"
					]
				}
			},
			"response": []
		},
		{
			"name": "Get UserLists For User",
			"protocolProfileBehavior": {
				"disableBodyPruning": true
			},
			"request": {
				"method": "GET",
				"header": [],
				"body": {
					"mode": "raw",
					"raw": "{\r\n    \"username\": \"admin\",\r\n    \"password\": \"password\"\r\n}",
					"options": {
						"raw": {
							"language": "json"
						}
					}
				},
				"url": {
					"raw": "localhost:9000/user/3/userlists",
					"host": [
						"localhost"
					],
					"port": "9000",
					"path": [
						"user",
						"3",
						"userlists"
					]
				}
			},
			"response": []
		},
		{
			"name": "Get UserLists For User and Game",
			"protocolProfileBehavior": {
				"disableBodyPruning": true
			},
			"request": {
				"method": "GET",
				"header": [],
				"body": {
					"mode": "raw",
					"raw": "{\r\n    \"username\": \"admin\",\r\n    \"password\": \"password\"\r\n}",
					"options": {
						"raw": {
							"language": "json"
						}
					}
				},
				"url": {
					"raw": "localhost:9000/user/3/game/4/userlists",
					"host": [
						"localhost"
					],
					"port": "9000",
					"path": [
						"user",
						"3",
						"game",
						"4",
						"userlists"
					]
				}
			},
			"response": []
		},
		{
			"name": "Get UserLists",
			"protocolProfileBehavior": {
				"disableBodyPruning": true
			},
			"request": {
				"method": "GET",
				"header": [],
				"body": {
					"mode": "raw",
					"raw": "{\r\n    \"username\": \"admin\",\r\n    \"password\": \"password\"\r\n}",
					"options": {
						"raw": {
							"language": "json"
						}
					}
				},
				"url": {
					"raw": "localhost:9000/userlist/4",
					"host": [
						"localhost"
					],
					"port": "9000",
					"path": [
						"userlist",
						"4"
					]
				}
			},
			"response": []
		},
		{
			"name": "Create UserList",
			"request": {
				"method": "POST",
				"header": [],
				"body": {
					"mode": "raw",
					"raw": "{\r\n    \"listType\": 4,\r\n    \"customType\": \"Super Awesome List\",\r\n    \"userId\": 3\r\n}",
					"options": {
						"raw": {
							"language": "json"
						}
					}
				},
				"url": {
					"raw": "localhost:9000/userlist",
					"host": [
						"localhost"
					],
					"port": "9000",
					"path": [
						"userlist"
					]
				}
			},
			"response": []
		},
		{
			"name": "Add Game to UserList",
			"request": {
				"method": "POST",
				"header": [],
				"body": {
					"mode": "raw",
					"raw": "{\r\n    \"listType\": 4,\r\n    \"customType\": \"Super Awesome List\",\r\n    \"userId\": 3\r\n}",
					"options": {
						"raw": {
							"language": "json"
						}
					}
				},
				"url": {
					"raw": "localhost:9000/userlistAdd/11/2239",
					"host": [
						"localhost"
					],
					"port": "9000",
					"path": [
						"userlistAdd",
						"11",
						"2239"
					]
				}
			},
			"response": []
		},
		{
			"name": "Remove Game From UserList",
			"request": {
				"method": "DELETE",
				"header": [],
				"body": {
					"mode": "raw",
					"raw": "{\r\n    \"listType\": 4,\r\n    \"customType\": \"Super Awesome List\",\r\n    \"userId\": 3\r\n}",
					"options": {
						"raw": {
							"language": "json"
						}
					}
				},
				"url": {
					"raw": "localhost:9000/userlistRemove/4/4",
					"host": [
						"localhost"
					],
					"port": "9000",
					"path": [
						"userlistRemove",
						"4",
						"4"
					]
				}
			},
			"response": []
		},
		{
			"name": "Delete UserList",
			"request": {
				"method": "DELETE",
				"header": [],
				"body": {
					"mode": "raw",
					"raw": "{\r\n    \"listType\": 4,\r\n    \"customType\": \"Super Awesome List\",\r\n    \"userId\": 3\r\n}",
					"options": {
						"raw": {
							"language": "json"
						}
					}
				},
				"url": {
					"raw": "localhost:9000/userlist/7",
					"host": [
						"localhost"
					],
					"port": "9000",
					"path": [
						"userlist",
						"7"
					]
				}
			},
			"response": []
		},
		{
			"name": "Update UserList",
			"request": {
				"method": "PUT",
				"header": [],
				"body": {
					"mode": "raw",
					"raw": "{\r\n    \"id\": 7,\r\n    \"listType\": 4,\r\n    \"customType\": \"Ultra Super Awesome List\",\r\n    \"userId\": 3,\r\n    \"games\": []\r\n}",
					"options": {
						"raw": {
							"language": "json"
						}
					}
				},
				"url": {
					"raw": "localhost:9000/userlist/7",
					"host": [
						"localhost"
					],
					"port": "9000",
					"path": [
						"userlist",
						"7"
					]
				}
			},
			"response": []
		},
		{
			"name": "Get Review",
			"protocolProfileBehavior": {
				"disableBodyPruning": true
			},
			"request": {
				"method": "GET",
				"header": [],
				"body": {
					"mode": "raw",
					"raw": "{\r\n    \"username\": \"admin\",\r\n    \"password\": \"password\"\r\n}",
					"options": {
						"raw": {
							"language": "json"
						}
					}
				},
				"url": {
					"raw": "localhost:9000/review/2",
					"host": [
						"localhost"
					],
					"port": "9000",
					"path": [
						"review",
						"2"
					]
				}
			},
			"response": []
		},
		{
			"name": "Delete Review",
			"request": {
				"method": "DELETE",
				"header": [],
				"body": {
					"mode": "raw",
					"raw": "{\r\n    \"username\": \"admin\",\r\n    \"password\": \"password\"\r\n}",
					"options": {
						"raw": {
							"language": "json"
						}
					}
				},
				"url": {
					"raw": "localhost:9000/review/2",
					"host": [
						"localhost"
					],
					"port": "9000",
					"path": [
						"review",
						"2"
					]
				}
			},
			"response": []
		},
		{
			"name": "Delete Comment",
			"request": {
				"method": "DELETE",
				"header": [],
				"body": {
					"mode": "raw",
					"raw": "{\r\n    \"username\": \"admin\",\r\n    \"password\": \"password\"\r\n}",
					"options": {
						"raw": {
							"language": "json"
						}
					}
				},
				"url": {
					"raw": "localhost:9000/comment/2",
					"host": [
						"localhost"
					],
					"port": "9000",
					"path": [
						"comment",
						"2"
					]
				}
			},
			"response": []
		},
		{
			"name": "Create Comment",
			"request": {
				"method": "POST",
				"header": [],
				"body": {
					"mode": "raw",
					"raw": "{\r\n    \"id\": 2,\r\n    \"commentText\": \"test\",\r\n    \"reviewId\": 1,\r\n    \"userId\": 3\r\n}",
					"options": {
						"raw": {
							"language": "json"
						}
					}
				},
				"url": {
					"raw": "localhost:9000/comment/",
					"host": [
						"localhost"
					],
					"port": "9000",
					"path": [
						"comment",
						""
					]
				}
			},
			"response": []
		},
		{
			"name": "Create Review",
			"request": {
				"method": "POST",
				"header": [],
				"body": {
					"mode": "raw",
					"raw": "{\r\n    \"id\": 5,\r\n    \"numberOfStars\": 4,\r\n    \"reviewText\": \"blah blah blah\",\r\n    \"replayabilityScore\": 3,\r\n    \"diversityScore\": 3,\r\n    \"aggroScore\": 3,\r\n    \"gameId\": 2,\r\n    \"userId\": 3\r\n}",
					"options": {
						"raw": {
							"language": "json"
						}
					}
				},
				"url": {
					"raw": "localhost:9000/review",
					"host": [
						"localhost"
					],
					"port": "9000",
					"path": [
						"review"
					]
				}
			},
			"response": []
		},
		{
			"name": "Update Comment",
			"request": {
				"method": "PUT",
				"header": [],
				"body": {
					"mode": "raw",
					"raw": "{\r\n    \"id\": 1,\r\n    \"commentText\": \"Actually I'm cool with this comment now\",\r\n    \"reviewId\": 1,\r\n    \"userId\": 3\r\n}",
					"options": {
						"raw": {
							"language": "json"
						}
					}
				},
				"url": {
					"raw": "localhost:9000/comment/1",
					"host": [
						"localhost"
					],
					"port": "9000",
					"path": [
						"comment",
						"1"
					]
				}
			},
			"response": []
		},
		{
			"name": "Update Review",
			"request": {
				"method": "PUT",
				"header": [],
				"body": {
					"mode": "raw",
					"raw": "{\r\n    \"id\": 2,\r\n    \"numberOfStars\": 4,\r\n    \"reviewText\": \"this review has been modified\",\r\n    \"replayabilityScore\": 3,\r\n    \"diversityScore\": 3,\r\n    \"aggroScore\": 3,\r\n    \"gameId\": 2,\r\n    \"userId\": 3\r\n}",
					"options": {
						"raw": {
							"language": "json"
						}
					}
				},
				"url": {
					"raw": "localhost:9000/review/2",
					"host": [
						"localhost"
					],
					"port": "9000",
					"path": [
						"review",
						"2"
					]
				}
			},
			"response": []
		},
		{
			"name": "Get Games By Title",
			"protocolProfileBehavior": {
				"disableBodyPruning": true
			},
			"request": {
				"method": "GET",
				"header": [],
				"body": {
					"mode": "raw",
					"raw": "{\r\n    \"username\": \"admin\",\r\n    \"password\": \"password\"\r\n}",
					"options": {
						"raw": {
							"language": "json"
						}
					}
				},
				"url": {
					"raw": "localhost:9000/game?stringSearch=Mario",
					"host": [
						"localhost"
					],
					"port": "9000",
					"path": [
						"game"
					],
					"query": [
						{
							"key": "stringSearch",
							"value": "Mario"
						}
					]
				}
			},
			"response": []
		}
	]
}